pyepwmorph/__init__.py
pyepwmorph/models/__init__.py
pyepwmorph/models/access.py
pyepwmorph/models/assemble.py
pyepwmorph/models/coordinate.py
pyepwmorph/morph/__init__.py
pyepwmorph/morph/procedures.py
pyepwmorph/tools/__init__.py
pyepwmorph/tools/cache.py
pyepwmorph/tools/configuration.py
pyepwmorph/tools/io.py
pyepwmorph/tools/ladybug_psychrometrics.py
pyepwmorph/tools/solar.py
pyepwmorph/tools/utilities.py
pyepwmorph/tools/workflow.py
pyepwmorph-1.0.5.dist-info/METADATA
pyepwmorph-1.0.5.dist-info/WHEEL
pyepwmorph-1.0.5.dist-info/licenses/LICENSE
pyepwmorph-1.0.5.dist-info/RECORD
