Metadata-Version: 2.4
Name: pyepwmorph
Version: 1.0.5
Summary: A python package to enable simple and easy gathering of climate model data and morphing of EPW files
Project-URL: Homepage, https://github.com/justinfmccarty/pyepwmorph
Project-URL: Issues, https://github.com/justinfmccarty/pyepwmorph/issues
Author-email: Justin McCarty <mccarty.justin.f@gmail.com>
License: GPL-3.0-or-later
License-File: LICENSE
Classifier: License :: OSI Approved :: GNU General Public License v3 or later (GPLv3+)
Classifier: Operating System :: OS Independent
Classifier: Programming Language :: Python :: 3
Classifier: Programming Language :: Python :: 3.9
Classifier: Programming Language :: Python :: 3.10
Classifier: Programming Language :: Python :: 3.11
Classifier: Programming Language :: Python :: 3.12
Requires-Python: >=3.9
Requires-Dist: dask>=2023.5.0
Requires-Dist: distributed>=2023.5.0
Requires-Dist: gcsfs>=2023.5.0
Requires-Dist: intake-esm>=2023.6.0
Requires-Dist: intake>=0.6.0
Requires-Dist: lz4>=4.0.0
Requires-Dist: meteocalc>=1.1.0
Requires-Dist: numpy>=1.20.0
Requires-Dist: pandas>=1.3.0
Requires-Dist: pvlib<1.0.0,>=0.13.0
Requires-Dist: pyarrow>=13.0.0
Requires-Dist: skyfield>=1.40
Requires-Dist: timezonefinder>=6.0.0
Requires-Dist: xarray>=2022.3.0
Requires-Dist: xclim>=0.40.0
Provides-Extra: dev
Requires-Dist: black>=23.0; extra == 'dev'
Requires-Dist: build>=0.10; extra == 'dev'
Requires-Dist: bump2version>=1.0; extra == 'dev'
Requires-Dist: flake8>=6.0; extra == 'dev'
Requires-Dist: ipykernel>=6.20.0; extra == 'dev'
Requires-Dist: isort>=5.0; extra == 'dev'
Requires-Dist: pytest-cov>=4.0; extra == 'dev'
Requires-Dist: pytest>=7.0; extra == 'dev'
Requires-Dist: twine>=4.0; extra == 'dev'
